Metadata-Version: 2.1
Name: typan
Version: 0.0.8
Summary: Extra features for Python
Home-page: https://bruhdev.com
Author: BruhDev
Author-email: mr.bruh.dev@gmail.com
License: UNKNOWN
Platform: UNKNOWN
Classifier: Programming Language :: Python :: 3
Classifier: License :: OSI Approved :: MIT License
Classifier: Operating System :: OS Independent
Requires-Python: >=3.6
